dash_charlotte/components/__init__.py
dash_charlotte/components/box.py
dash_charlotte/components/button.py
dash_charlotte/components/dashboard.py
dash_charlotte/components/drawer.py
dash_charlotte/components/footer.py
dash_charlotte/components/navbar.py
dash_charlotte/components/table.py
dash_charlotte/layouts/__init__.py
dash_charlotte/layouts/login.py
dash_charlotte/layouts/not_found_404.py
dash_charlotte/themes/__init__.py
dash_charlotte/themes/bootstrap.py
dash_charlotte/themes/charlotte_dark.py
dash_charlotte/themes/charlotte_light.py
dash_charlotte/themes/colorblind.py
dash_charlotte/themes/colors.py
dash_charlotte/themes/dracula.py
dash_charlotte/themes/fonts.py
dash_charlotte/themes/icons.py
dash_charlotte/themes/themes.py
dash_charlotte-0.3.1.dist-info/LICENSE
dash_charlotte-0.3.1.dist-info/METADATA
dash_charlotte-0.3.1.dist-info/WHEEL
dash_charlotte-0.3.1.dist-info/top_level.txt
dash_charlotte-0.3.1.dist-info/RECORD
