Metadata-Version: 2.1
Name: dash-charlotte
Version: 0.3.1
Summary: A package of themes, tools and components for Plotly-Dash web dashboards.
Home-page: https://github.com/GusFurtado/dash-charlotte
Author: Gustavo Furtado
Author-email: gustavofurtado2@gmail.com
License: MIT
Download-URL: https://github.com/GusFurtado/dash-charlotte/archive/0.3.1.tar.gz
Keywords: dashboard,plotly
Platform: UNKNOWN
Classifier: Development Status :: 2 - Pre-Alpha
Classifier: Intended Audience :: Developers
Classifier: Topic :: Software Development :: Build Tools
Classifier: Topic :: Software Development :: Libraries :: Python Modules
Classifier: Topic :: Software Development :: User Interfaces
Classifier: License :: OSI Approved :: MIT License
Classifier: Natural Language :: English
Classifier: Programming Language :: Python :: 3
Classifier: Programming Language :: Python :: 3.6
License-File: LICENSE
Requires-Dist: dash
Requires-Dist: dash-bootstrap-components
